safe_return/__init__.py
safe_return-1.0.0.dist-info/licenses/LICENSE
safe_return-1.0.0.dist-info/METADATA
safe_return-1.0.0.dist-info/WHEEL
safe_return-1.0.0.dist-info/top_level.txt
safe_return-1.0.0.dist-info/RECORD
