Metadata-Version: 2.4
Name: safe-return
Version: 1.0.0
Summary: Safe return math str
Author: Luka
Author-email: <luka.m21@hotmail.com>
License: MIT License
Keywords: math,expression
Classifier: Topic :: Scientific/Engineering :: Mathematics
Classifier: Development Status :: 5 - Production/Stable
Classifier: Programming Language :: Python :: 3
License-File: LICENSE
Dynamic: author
Dynamic: author-email
Dynamic: classifier
Dynamic: description
Dynamic: description-content-type
Dynamic: keywords
Dynamic: license
Dynamic: license-file
Dynamic: summary
